{
  "$schema": "https://json-schema.org/draft-07/schema#",
  "$id": "https://gitlab.com/alienspaces/go-mud/server/schema/dungeoncharacter/data.schema.json",
  "title": "Character Data",
  "description": "Character data",
  "type": "object",
  "required": [
    "id",
    "dungeon_id",
    "dungeon_location_id",
    "name",
    "strength",
    "dexterity",
    "intelligence",
    "health",
    "fatigue",
    "coins",
    "experience_points",
    "attribute_points",
    "created_at"
  ],
  "properties": {
    "id": {
      "type": "string",
      "format": "uuid"
    },
    "dungeon_id": {
      "type": "string",
      "format": "uuid"
    },
    "dungeon_location_id": {
      "type": "string",
      "format": "uuid"
    },
    "name": {
      "type": "string"
    },
    "strength": {
      "type": "number"
    },
    "dexterity": {
      "type": "number"
    },
    "intelligence": {
      "type": "number"
    },
    "health": {
      "type": "number"
    },
    "fatigue": {
      "type": "number"
    },
    "coins": {
      "type": "number"
    },
    "experience_points": {
      "type": "number"
    },
    "attribute_points": {
      "type": "number"
    },
    "points": {
      "type": "number"
    },
    "created_at": {
      "type": "string",
      "format": "date-time"
    },
    "updated_at": {
      "type": "string",
      "format": "date-time"
    }
  }
}
